atlas_provider_sqlalchemy/__init__.py
atlas_provider_sqlalchemy/ddl.py
atlas_provider_sqlalchemy/main.py
atlas_provider_sqlalchemy/parser.py
atlas_provider_sqlalchemy-0.5.0.dist-info/METADATA
atlas_provider_sqlalchemy-0.5.0.dist-info/WHEEL
atlas_provider_sqlalchemy-0.5.0.dist-info/entry_points.txt
atlas_provider_sqlalchemy-0.5.0.dist-info/licenses/LICENSE
atlas_provider_sqlalchemy-0.5.0.dist-info/RECORD
